strategoutil.py
strategoutil-0.1.4.dist-info/LICENSE
strategoutil-0.1.4.dist-info/METADATA
strategoutil-0.1.4.dist-info/WHEEL
strategoutil-0.1.4.dist-info/top_level.txt
strategoutil-0.1.4.dist-info/RECORD
