Metadata-Version: 2.1
Name: strategoutil
Version: 0.1.4
Summary: Python utility functions library for UPPAAL Stratego
Author: Mihhail Samusev, Martijn Goorden
Author-email: msam@build.aau.dk, magoorden@cs.aau.dk
License: MIT
Project-URL: Source, https://github.com/DEIS-Tools/strategoutil
Project-URL: Tracker, https://github.com/DEIS-Tools/strategoutil/issues
Keywords: uppaal,stratego,MPC
Classifier: Programming Language :: Python :: 3
Classifier: License :: OSI Approved :: MIT License
Classifier: Operating System :: OS Independent
Requires-Python: >=3.6
License-File: docs/LICENSE
Provides-Extra: test
Requires-Dist: pytest ; extra == 'test'
